tycki.cpython-310-x86_64-linux-gnu.so
tycki-0.0.8.dist-info/LICENSE
tycki-0.0.8.dist-info/WHEEL
tycki-0.0.8.dist-info/NOTICE.txt
tycki-0.0.8.dist-info/top_level.txt
tycki-0.0.8.dist-info/METADATA
tycki-0.0.8.dist-info/RECORD
